<?xml version="1.0" encoding="UTF-8"?>
<HR_DATA>
  <EMPLOYEES>
    <EMPLOYEE>
      <EMPLOYEE_ID>100</EMPLOYEE_ID>
      <FIRST_NAME>Steven</FIRST_NAME>
      <LAST_NAME>King</LAST_NAME>
      <EMAIL>steven.king@example.com</EMAIL>
      <PHONE_NUMBER>515.123.4567</PHONE_NUMBER>
      <HIRE_DATE>2003-06-17</HIRE_DATE>
      <JOB_ID>AD_PRES</JOB_ID>
      <SALARY>24000.00</SALARY>
      <COMMISSION_PCT/>
      <MANAGER_ID/>
      <DEPARTMENT_ID>10</DEPARTMENT_ID>
    </EMPLOYEE>
    <EMPLOYEE>
      <EMPLOYEE_ID>101</EMPLOYEE_ID>
      <FIRST_NAME>Neena</FIRST_NAME>
      <LAST_NAME>Kochhar</LAST_NAME>
      <EMAIL>neena.kochhar@example.com</EMAIL>
      <PHONE_NUMBER>515.123.4568</PHONE_NUMBER>
      <HIRE_DATE>2005-09-21</HIRE_DATE>
      <JOB_ID>AD_VP</JOB_ID>
      <SALARY>17000.00</SALARY>
      <COMMISSION_PCT/>
      <MANAGER_ID>100</MANAGER_ID>
      <DEPARTMENT_ID>10</DEPARTMENT_ID>
    </EMPLOYEE>
    <EMPLOYEE>
      <EMPLOYEE_ID>102</EMPLOYEE_ID>
      <FIRST_NAME>Lex</FIRST_NAME>
      <LAST_NAME>De Haan</LAST_NAME>
      <EMAIL>lex.dehaan@example.com</EMAIL>
      <PHONE_NUMBER>515.123.4569</PHONE_NUMBER>
      <HIRE_DATE>2001-01-13</HIRE_DATE>
      <JOB_ID>AD_VP</JOB_ID>
      <SALARY>17000.00</SALARY>
      <COMMISSION_PCT/>
      <MANAGER_ID>100</MANAGER_ID>
      <DEPARTMENT_ID>10</DEPARTMENT_ID>
    </EMPLOYEE>
    <EMPLOYEE>
      <EMPLOYEE_ID>103</EMPLOYEE_ID>
      <FIRST_NAME>John</FIRST_NAME>
      <LAST_NAME>Chen</LAST_NAME>
      <EMAIL>john.chen@example.com</EMAIL>
      <PHONE_NUMBER>515.123.4567</PHONE_NUMBER>
      <HIRE_DATE>2005-09-28</HIRE_DATE>
      <JOB_ID>AD_ASST</JOB_ID>
      <SALARY>9000.00</SALARY>
      <COMMISSION_PCT/>
      <MANAGER_ID>102</MANAGER_ID>
      <DEPARTMENT_ID>10</DEPARTMENT_ID>
    </EMPLOYEE>
    <EMPLOYEE>
      <EMPLOYEE_ID>104</EMPLOYEE_ID>
      <FIRST_NAME>Janette</FIRST_NAME>
      <LAST_NAME>King</LAST_NAME>
      <EMAIL>janette.king@example.com</EMAIL>
      <PHONE_NUMBER>515.123.4568</PHONE_NUMBER>
      <HIRE_DATE>2004-01-30</HIRE_DATE>
      <JOB_ID>AD_ASST</JOB_ID>
      <SALARY>8200.00</SALARY>
      <COMMISSION_PCT/>
      <MANAGER_ID>103</MANAGER_ID>
      <DEPARTMENT_ID>10</DEPARTMENT_ID>
    </EMPLOYEE>
  </EMPLOYEES>

  <DEPARTMENTS>
    <DEPARTMENT>
      <DEPARTMENT_ID>10</DEPARTMENT_ID>
      <DEPARTMENT_NAME>Administration</DEPARTMENT_NAME>
      <MANAGER_ID>200</MANAGER_ID>
      <LOCATION_ID>1700</LOCATION_ID>
    </DEPARTMENT>
    <DEPARTMENT>
      <DEPARTMENT_ID>20</DEPARTMENT_ID>
      <DEPARTMENT_NAME>Marketing</DEPARTMENT_NAME>
      <MANAGER_ID>201</MANAGER_ID>
      <LOCATION_ID>1800</LOCATION_ID>
    </DEPARTMENT>
    <DEPARTMENT>
      <DEPARTMENT_ID>30</DEPARTMENT_ID>
      <DEPARTMENT_NAME>Sales</DEPARTMENT_NAME>
      <MANAGER_ID>202</MANAGER_ID>
      <LOCATION_ID>1900</LOCATION_ID>
    </DEPARTMENT>
    <DEPARTMENT>
      <DEPARTMENT_ID>40</DEPARTMENT_ID>
      <DEPARTMENT_NAME>Human Resources</DEPARTMENT_NAME>
      <MANAGER_ID>203</MANAGER_ID>
      <LOCATION_ID>2000</LOCATION_ID>
    </DEPARTMENT>
    <DEPARTMENT>
      <DEPARTMENT_ID>50</DEPARTMENT_ID>
      <DEPARTMENT_NAME>Finance</DEPARTMENT_NAME>
      <MANAGER_ID>204</MANAGER_ID>
      <LOCATION_ID>2100</LOCATION_ID>
    </DEPARTMENT>
  </DEPARTMENTS>

  <JOBS>
    <JOB>
      <JOB_ID>AD_PRES</JOB_ID>
      <JOB_TITLE>President</JOB_TITLE>
      <MIN_SALARY>20000</MIN_SALARY>
      <MAX_SALARY>40000</MAX_SALARY>
    </JOB>
    <JOB>
      <JOB_ID>AD_VP</JOB_ID>
      <JOB_TITLE>Administration Vice President</JOB_TITLE>
      <MIN_SALARY>15000</MIN_SALARY>
      <MAX_SALARY>30000</MAX_SALARY>
    </JOB>
    <JOB>
      <JOB_ID>AD_ASST</JOB_ID>
      <JOB_TITLE>Administration Assistant</JOB_TITLE>
      <MIN_SALARY>3000</MIN_SALARY>
      <MAX_SALARY>6000</MAX_SALARY>
    </JOB>
    <JOB>
      <JOB_ID>FI_MGR</JOB_ID>
      <JOB_TITLE>Finance Manager</JOB_TITLE>
      <MIN_SALARY>8200</MIN_SALARY>
      <MAX_SALARY>16000</MAX_SALARY>
    </JOB>
    <JOB>
      <JOB_ID>FI_ACCOUNT</JOB_ID>
      <JOB_TITLE>Accountant</JOB_TITLE>
      <MIN_SALARY>4200</MIN_SALARY>
      <MAX_SALARY>9000</MAX_SALARY>
    </JOB>
  </JOBS>


  <JOB_HISTORY>
    <JOB_HISTORY>
      <EMPLOYEE_ID>100</EMPLOYEE_ID>
      <START_DATE>2003-06-17</START_DATE>
      <END_DATE>2005-07-24</END_DATE>
      <JOB_ID>AD_PRES</JOB_ID>
      <DEPARTMENT_ID>10</DEPARTMENT_ID>
    </JOB_HISTORY>
    <JOB_HISTORY>
      <EMPLOYEE_ID>101</EMPLOYEE_ID>
      <START_DATE>2005-09-21</START_DATE>
      <END_DATE>2007-06-23</END_DATE>
      <JOB_ID>AD_VP</JOB_ID>
      <DEPARTMENT_ID>10</DEPARTMENT_ID>
    </JOB_HISTORY>
    <JOB_HISTORY>
      <EMPLOYEE_ID>102</EMPLOYEE_ID>
      <START_DATE>2001-01-13</START_DATE>
      <END_DATE>2005-09-21</END_DATE>
      <JOB_ID>AD_VP</JOB_ID>
      <DEPARTMENT_ID>10</DEPARTMENT_ID>
    </JOB_HISTORY>
    <JOB_HISTORY>
      <EMPLOYEE_ID>103</EMPLOYEE_ID>
      <START_DATE>2005-09-28</START_DATE>
      <END_DATE>2006-09-30</END_DATE>
      <JOB_ID>AD_ASST</JOB_ID>
      <DEPARTMENT_ID>10</DEPARTMENT_ID>
    </JOB_HISTORY>
    <JOB_HISTORY>
      <EMPLOYEE_ID>104</EMPLOYEE_ID>
      <START_DATE>2004-01-30</START_DATE>
      <END_DATE>2005-05-07</END_DATE>
      <JOB_ID>AD_ASST</JOB_ID>
      <DEPARTMENT_ID>10</DEPARTMENT_ID>
    </JOB_HISTORY>
  </JOB_HISTORY>

  <COUNTRIES>
    <COUNTRY>
      <COUNTRY_ID>US</COUNTRY_ID>
      <COUNTRY_NAME>United States</COUNTRY_NAME>
      <REGION_ID>2</REGION_ID>
    </COUNTRY>
    <COUNTRY>
      <COUNTRY_ID>CA</COUNTRY_ID>
      <COUNTRY_NAME>Canada</COUNTRY_NAME>
      <REGION_ID>2</REGION_ID>
    </COUNTRY>
    <COUNTRY>
      <COUNTRY_ID>UK</COUNTRY_ID>
      <COUNTRY_NAME>United Kingdom</COUNTRY_NAME>
      <REGION_ID>1</REGION_ID>
    </COUNTRY>
    <COUNTRY>
      <COUNTRY_ID>FR</COUNTRY_ID>
      <COUNTRY_NAME>France</COUNTRY_NAME>
      <REGION_ID>1</REGION_ID>
    </COUNTRY>
    <COUNTRY>
      <COUNTRY_ID>JP</COUNTRY_ID>
      <COUNTRY_NAME>Japan</COUNTRY_NAME>
      <REGION_ID>3</REGION_ID>
    </COUNTRY>
  </COUNTRIES>

  <REGIONS>
    <REGION>
      <REGION_ID>1</REGION_ID>
      <REGION_NAME>Europe</REGION_NAME>
    </REGION>
    <REGION>
      <REGION_ID>2</REGION_ID>
      <REGION_NAME>Americas</REGION_NAME>
    </REGION>
    <REGION>
      <REGION_ID>3</REGION_ID>
      <REGION_NAME>Asia</REGION_NAME>
    </REGION>
  </REGIONS>

</HR_DATA>



<!ELEMENT JOB_ID (#PCDATA)>
<!ELEMENT SALARY (#PCDATA)>
<!ELEMENT COMMISSION_PCT (#PCDATA)>
<!ELEMENT MANAGER_ID (#PCDATA)>
<!ELEMENT DEPARTMENT_ID (#PCDATA)>